machinestate.py
forkedmachinestate-0.6.2.dist-info/licenses/LICENSE
forkedmachinestate-0.6.2.dist-info/METADATA
forkedmachinestate-0.6.2.dist-info/WHEEL
forkedmachinestate-0.6.2.dist-info/entry_points.txt
forkedmachinestate-0.6.2.dist-info/top_level.txt
forkedmachinestate-0.6.2.dist-info/RECORD
