Metadata-Version: 2.4
Name: ForkedMachineState
Version: 0.6.2
Summary: Gathering the system state before benchmarking and other tests on compute systems.
Author-email: Thomas Gruber <thomas.gruber@fau.de>, Jan Laukemann <jan.laukemann@fau.de>, Julian Hammer <julian.hammer@fau.de>
License: GPL-3.0-or-later
Project-URL: Homepage, https://github.com/RRZE-HPC/MachineState
Project-URL: Issues, https://github.com/RRZE-HPC/MachineState/issues
Keywords: benchmarking,linux,system state,topology
Classifier: Development Status :: 3 - Alpha
Classifier: Intended Audience :: Science/Research
Classifier: Intended Audience :: Developers
Classifier: Intended Audience :: System Administrators
Classifier: License :: OSI Approved :: GNU General Public License v3 or later (GPLv3+)
Classifier: Topic :: System :: Benchmark
Classifier: Topic :: System :: Hardware
Classifier: Topic :: System :: Operating System
Classifier: Topic :: System :: Systems Administration
Classifier: Topic :: Education :: Testing
Classifier: Operating System :: POSIX :: Linux
Classifier: Environment :: Console
Classifier: Programming Language :: Python :: 3
Requires-Python: >=3.6
License-File: LICENSE
Dynamic: license-file
